wfs_downloader/__init__.py
wfs_downloader/download.py
wfs_downloader-1.2.0.dist-info/LICENSE
wfs_downloader-1.2.0.dist-info/METADATA
wfs_downloader-1.2.0.dist-info/WHEEL
wfs_downloader-1.2.0.dist-info/entry_points.txt
wfs_downloader-1.2.0.dist-info/top_level.txt
wfs_downloader-1.2.0.dist-info/RECORD
