Metadata-Version: 2.1
Name: wfs-downloader
Version: 1.2.0
Summary: Downloads GML files from a WFS service in a pseudo-paginated way using bounding boxes and combine them again to one file.
Home-page: https://github.com/codeforberlin/wfs-downloader
Author: Jochen Klar
Author-email: mail@jochenklar.de
Maintainer: Jochen Klar
Maintainer-email: mail@jochenklar.de
License: MIT
Platform: UNKNOWN
License-File: LICENSE
Requires-Dist: PyYAML
